dentmark/__init__.py
dentmark/defs_manager.py
dentmark/dentmark.py
dentmark/parser.py
dentmark/tag_def.py
dentmark/text_node.py
dentmark/default_definitions/__init__.py
dentmark/default_definitions/anchor.py
dentmark/default_definitions/annotation.py
dentmark/default_definitions/emphasis.py
dentmark/default_definitions/headlines.py
dentmark/default_definitions/images.py
dentmark/default_definitions/lists.py
dentmark/default_definitions/tables.py
dentmark/default_definitions/youtube.py
dentmark-0.0.9.dist-info/LICENSE
dentmark-0.0.9.dist-info/METADATA
dentmark-0.0.9.dist-info/WHEEL
dentmark-0.0.9.dist-info/top_level.txt
dentmark-0.0.9.dist-info/RECORD
