Metadata-Version: 2.1
Name: dentmark
Version: 0.0.9
Summary: An indentation-delimited, configurable markdown language
Home-page: https://www.transvec.com/dentmark
Author: Ryli Dunlap
Author-email: ryli@transvec.com
License: UNKNOWN
Platform: UNKNOWN
Classifier: Programming Language :: Python :: 3
Classifier: License :: OSI Approved :: GNU General Public License v3 (GPLv3)
Classifier: Operating System :: OS Independent
Requires-Python: >=3.6
